[
  {
    "brand": "Tom's Vlog  in Asia",
    "posts": 1,
    "shareOfVoice": 0.0,
    "engagementRate": 0.0,
    "sentimentRatio": 0
  },
  {
    "brand": "BeatVn Official ",
    "posts": 1,
    "shareOfVoice": 0.01,
    "engagementRate": 0.9119,
    "sentimentRatio": 0
  },
  {
    "brand": "Taichinhso News",
    "posts": 1,
    "shareOfVoice": 0.01,
    "engagementRate": 0.7989,
    "sentimentRatio": 0
  },
  {
    "brand": "VTC NEWS",
    "posts": 1,
    "shareOfVoice": 0.11,
    "engagementRate": 0.7266,
    "sentimentRatio": 0
  },
  {
    "brand": "Beanlatteart",
    "posts": 6,
    "shareOfVoice": 0.25,
    "engagementRate": 0.5384,
    "sentimentRatio": 0
  },
  {
    "brand": "Phuc Long",
    "posts": 25,
    "shareOfVoice": 0.2,
    "engagementRate": 0.4663,
    "sentimentRatio": 0
  },
  {
    "brand": "JB CHANNEL",
    "posts": 1,
    "shareOfVoice": 0.01,
    "engagementRate": 0.6711,
    "sentimentRatio": 0
  },
  {
    "brand": "Highlands Coffee Vietnam",
    "posts": 25,
    "shareOfVoice": 99.4,
    "engagementRate": 0.8752,
    "sentimentRatio": 0
  },
  {
    "brand": "Mật Mã Thương Trường",
    "posts": 1,
    "shareOfVoice": 0.0,
    "engagementRate": 1.6611,
    "sentimentRatio": 0
  },
  {
    "brand": "all about Vietnam  USA ",
    "posts": 1,
    "shareOfVoice": 0.0,
    "engagementRate": 2.1739,
    "sentimentRatio": 0
  },
  {
    "brand": "The Toilets in Vietnam and the World",
    "posts": 2,
    "shareOfVoice": 0.01,
    "engagementRate": 2.308,
    "sentimentRatio": 0
  }
]